sl_creatio_connector/constants.py
sl_creatio_connector/creatio.py
sl_creatio_connector-0.1.7.dist-info/METADATA
sl_creatio_connector-0.1.7.dist-info/WHEEL
sl_creatio_connector-0.1.7.dist-info/RECORD
