Metadata-Version: 2.1
Name: sl-creatio-connector
Version: 0.1.7
Summary: Creatio (aka BPMonline) ODATA API helper
Author: sumarokov-vp
Author-email: sumarokov.vp@gmail.com
Requires-Python: >=3.11,<4.0
Classifier: Programming Language :: Python :: 3
Classifier: Programming Language :: Python :: 3.11
Requires-Dist: pytest (>=7.2.0,<8.0.0)
Requires-Dist: requests (>=2.28.1,<3.0.0)
